stvtermux/__init__.py
stvtermux/cli.py
stvtermux/core.py
stvtermux/index.py
stvtermux/nhom.py
stvtermux-1.0.8.dist-info/METADATA
stvtermux-1.0.8.dist-info/WHEEL
stvtermux-1.0.8.dist-info/entry_points.txt
stvtermux-1.0.8.dist-info/top_level.txt
stvtermux-1.0.8.dist-info/RECORD
