Metadata-Version: 2.4
Name: stvtermux
Version: 1.0.8
Requires-Dist: requests
Dynamic: requires-dist
